libname/__init__.py
libname/hello.py
libname/models/CudaSift-Pascal.zip
libname/models/opencv_contrib-4.10.0.zip
SIFTY_3.1.0-3.1.0.dist-info/METADATA
SIFTY_3.1.0-3.1.0.dist-info/WHEEL
SIFTY_3.1.0-3.1.0.dist-info/top_level.txt
SIFTY_3.1.0-3.1.0.dist-info/RECORD
