Metadata-Version: 2.1
Name: SIFTY-3.1.0
Version: 3.1.0
Summary: SIFTY
Author: Malyoneeeeer
Author-email: <malyoneeeeer@yahoo.com>
Keywords: python
Classifier: Development Status :: 1 - Planning
Classifier: Intended Audience :: Developers
Classifier: Programming Language :: Python :: 3
Classifier: Operating System :: Microsoft :: Windows
Requires-Dist: opencv-python
